{
  "paragraph": {
    "paragraphtext": [
      {
        "text": "The Canadian and United States governments have identified more than 30 critical minerals or materials which policy makers regard as essential for the energy transition and the decarbonization of our economies. The governments are."},
        { 
          "text": "providing financial support",
          "underlineColor": "black"
        },
        { 
          "text": "and challenging companies to develop new mines to enhance production within North America in order to reduce our dependence on importing these minerals from other countries."
      }
    ],
    "variant": "h4",
    "align": [
      "left"
    ]
  }
}